{
  "sections": {
    "header": {
      "type": "header"
    },
    "banner": {
      "type": "banner"
    },
    "shopCarrossel": {
      "type": "shopCarrossel"
    },
    "uvps": {
      "type": "uvps"
    },
    "socialProf": {
      "type": "socialProf"
    },
    "bestSell1": {
      "type": "bestSell"
    },
    "review": {
      "type": "review"
    },
    "bestSell2": {
      "type": "bestSell"
    },
    "faqs": {
      "type": "faqs"
    },
    "footer": {
      "type": "footer"
    }
  },
  "order": [
    "header",
    "banner",
    "shopCarrossel",
    "uvps",
    "socialProf",
    "bestSell1",
    "review",
    "bestSell2",
    "faqs",
    "footer"
  ]
}